setup.cfg
setup.py
django_mixinvideos.egg-info/PKG-INFO
django_mixinvideos.egg-info/SOURCES.txt
django_mixinvideos.egg-info/dependency_links.txt
django_mixinvideos.egg-info/top_level.txt
mixin_videos/__init__.py
mixin_videos/admin.py
mixin_videos/mixins.py
mixin_videos/models.py
mixin_videos/tests.py
mixin_videos/views.py