Metadata-Version: 1.0
Name: django-mixinvideos
Version: 0.1.2
Summary: Mixin for videos
Home-page: https://github.com/edussilva/django-mixinvideos
Author: Eduardo Silva
Author-email: edussilva@live.com
License: UNKNOWN
Keywords: django mixins mixin video videos
Platform: UNKNOWN
